<?xml version="1.0" encoding="utf-8"?><demos>
    <name>Ordered_Tec</name>
    <type>toolbox</type>
    <icon>HelpIcon.DEMOS</icon>
    <description>This text appears on the main page for your examples.</description>
    <website><a href="http://www.mathworks.com">Link to your Web site</a></website>
    
    <demosection>
        <demoitem>
            <label>Getting Start</label>
            <type>M-file</type>
            <source>example_01</source>
        </demoitem>
        <demoitem>
            <label>Multi-Zone</label>
            <type>M-file</type>
            <source>mainpage</source>
        </demoitem>
        <demoitem>
            <label>Grid and Solution</label>
            <type>M-file</type>
            <source>mainpage</source>
        </demoitem>
        <demoitem>
            <label>Unsteady Solution</label>
            <type>M-file</type>
            <source>mainpage</source>
        </demoitem>
        <demoitem>
            <label>Data Type</label>
            <type>M-file</type>
            <source>mainpage</source>
        </demoitem>
        <demoitem>
            <label>Log System</label>
            <type>M-file</type>
            <source>mainpage</source>
        </demoitem>
    </demosection>
    
</demos>